tap_geekbot/__init__.py
tap_geekbot/__main__.py
tap_geekbot/client.py
tap_geekbot/streams.py
tap_geekbot/tap.py
tap_geekbot-0.6.1.dist-info/METADATA
tap_geekbot-0.6.1.dist-info/WHEEL
tap_geekbot-0.6.1.dist-info/entry_points.txt
tap_geekbot-0.6.1.dist-info/licenses/LICENSE
tap_geekbot-0.6.1.dist-info/RECORD
