Metadata-Version: 2.4
Name: tap-geekbot
Version: 0.6.1
Summary: Singer tap for Geekbot, built with the Meltano SDK for Singer Taps.
License-Expression: Apache-2.0
License-File: LICENSE
Keywords: ELT,Geekbot,singer.io
Author: Edgar Ramírez-Mondragón
Author-email: edgarrm358@gmail.com
Requires-Python: >=3.10,<4
Classifier: License :: OSI Approved :: Apache Software License
Classifier: Programming Language :: Python :: 3 :: Only
Classifier: Programming Language :: Python :: 3.10
Classifier: Programming Language :: Python :: 3.11
Classifier: Programming Language :: Python :: 3.12
Classifier: Programming Language :: Python :: 3.13
Classifier: Programming Language :: Python :: 3.14
Requires-Dist: singer-sdk (>=0.51.0,<0.52.0)
Requires-Dist: typing-extensions (>=4.15,<5) ; python_version < "3.12"
Project-URL: Documentation, https://github.com/reservoir-data/tap-geekbot#readme
Project-URL: Homepage, https://github.com/reservoir-data/tap-geekbot
Project-URL: Repository, https://github.com/reservoir-data/tap-geekbot
